snmp_py_lite/__init__.py
snmp_py_lite/client.py
snmp_py_lite/constants.py
snmp_py_lite/encoder.py
snmp_py_lite/format.py
snmp_py_lite/message.py
snmp_py_lite/transport.py
snmp_py_lite-0.1.0.dist-info/LICENSE
snmp_py_lite-0.1.0.dist-info/METADATA
snmp_py_lite-0.1.0.dist-info/WHEEL
snmp_py_lite-0.1.0.dist-info/top_level.txt
snmp_py_lite-0.1.0.dist-info/RECORD
