Metadata-Version: 2.1
Name: snmp_py_lite
Version: 0.1.0
Summary: SNMP Python Library
Home-page: https://github.com/katzeNilpferd/SnmpPyLite
Author: Evgeny Ockatiev
Author-email: evgeny.ockatiev@gmail.com
Classifier: Programming Language :: Python :: 3
Classifier: License :: OSI Approved :: MIT License
Classifier: Operating System :: OS Independent
Requires-Python: >=3.6
License-File: LICENSE
Provides-Extra: dev
Requires-Dist: pytest; extra == "dev"
Requires-Dist: flake8; extra == "dev"
